async_2captcha_solver/__init__.py
async_2captcha_solver/client.py
async_2captcha_solver/enums.py
async_2captcha_solver/exceptions.py
async_2captcha_solver/logs_config.py
async_2captcha_solver/py.typed
async_2captcha_solver/types.py
async_2captcha_solver-0.2.1.dist-info/LICENSE
async_2captcha_solver-0.2.1.dist-info/METADATA
async_2captcha_solver-0.2.1.dist-info/WHEEL
async_2captcha_solver-0.2.1.dist-info/top_level.txt
async_2captcha_solver-0.2.1.dist-info/RECORD
