Metadata-Version: 2.2
Name: async_2captcha_solver
Version: 0.2.1
Summary: An Async wrapper for 2captcha solver API
Author-email: Rune Tech <runetech2024@gmail.com>
License: The MIT License (MIT)
Project-URL: Homepage, https://github.com/runetech0/async_2captcha_wrapper
Project-URL: github, https://github.com/runetech0/async_2captcha_wrapper
Keywords: async,2captcha,2captcha.com,captcha,solver
Requires-Python: >=3.11
License-File: LICENSE
Requires-Dist: aiohttp>=3.10.10
Requires-Dist: aiohttp_socks>=0.9.0
